Decryption/InvSBox.v

module InvSBox (
    input wire [7:0] in_toSub,
    output wire [7:0] out_Subed
);
    
wire [7:0] new_inv_sbox[8'hff:8'h00];

assign new_inv_sbox[8'h00] = 8'h52;
assign new_inv_sbox[8'h01] = 8'h09;
assign new_inv_sbox[8'h02] = 8'h6a;
assign new_inv_sbox[8'h03] = 8'hd5;
assign new_inv_sbox[8'h04] = 8'h30;
assign new_inv_sbox[8'h05] = 8'h36;
assign new_inv_sbox[8'h06] = 8'ha5;
assign new_inv_sbox[8'h07] = 8'h38;
assign new_inv_sbox[8'h08] = 8'hbf;
assign new_inv_sbox[8'h09] = 8'h40;
assign new_inv_sbox[8'h0a] = 8'ha3;
assign new_inv_sbox[8'h0b] = 8'h9e;
assign new_inv_sbox[8'h0c] = 8'h81;
assign new_inv_sbox[8'h0d] = 8'hf3;
assign new_inv_sbox[8'h0e] = 8'hd7;
assign new_inv_sbox[8'h0f] = 8'hfb;
assign new_inv_sbox[8'h10] = 8'h7c;
assign new_inv_sbox[8'h11] = 8'he3;
assign new_inv_sbox[8'h12] = 8'h39;
assign new_inv_sbox[8'h13] = 8'h82;
assign new_inv_sbox[8'h14] = 8'h9b;
assign new_inv_sbox[8'h15] = 8'h2f;
assign new_inv_sbox[8'h16] = 8'hff;
assign new_inv_sbox[8'h17] = 8'h87;
assign new_inv_sbox[8'h18] = 8'h34;
assign new_inv_sbox[8'h19] = 8'h8e;
assign new_inv_sbox[8'h1a] = 8'h43;
assign new_inv_sbox[8'h1b] = 8'h44;
assign new_inv_sbox[8'h1c] = 8'hc4;
assign new_inv_sbox[8'h1d] = 8'hde;
assign new_inv_sbox[8'h1e] = 8'he9;
assign new_inv_sbox[8'h1f] = 8'hcb;
assign new_inv_sbox[8'h20] = 8'h54;
assign new_inv_sbox[8'h21] = 8'h7b;
assign new_inv_sbox[8'h22] = 8'h94;
assign new_inv_sbox[8'h23] = 8'h32;
assign new_inv_sbox[8'h24] = 8'ha6;
assign new_inv_sbox[8'h25] = 8'hc2;
assign new_inv_sbox[8'h26] = 8'h23;
assign new_inv_sbox[8'h27] = 8'h3d;
assign new_inv_sbox[8'h28] = 8'hee;
assign new_inv_sbox[8'h29] = 8'h4c;
assign new_inv_sbox[8'h2a] = 8'h95;
assign new_inv_sbox[8'h2b] = 8'h0b;
assign new_inv_sbox[8'h2c] = 8'h42;
assign new_inv_sbox[8'h2d] = 8'hfa;
assign new_inv_sbox[8'h2e] = 8'hc3;
assign new_inv_sbox[8'h2f] = 8'h4e;
assign new_inv_sbox[8'h30] = 8'h08;
assign new_inv_sbox[8'h31] = 8'h2e;
assign new_inv_sbox[8'h32] = 8'ha1;
assign new_inv_sbox[8'h33] = 8'h66;
assign new_inv_sbox[8'h34] = 8'h28;
assign new_inv_sbox[8'h35] = 8'hd9;
assign new_inv_sbox[8'h36] = 8'h24;
assign new_inv_sbox[8'h37] = 8'hb2;
assign new_inv_sbox[8'h38] = 8'h76;
assign new_inv_sbox[8'h39] = 8'h5b;
assign new_inv_sbox[8'h3a] = 8'ha2;
assign new_inv_sbox[8'h3b] = 8'h49;
assign new_inv_sbox[8'h3c] = 8'h6d;
assign new_inv_sbox[8'h3d] = 8'h8b;
assign new_inv_sbox[8'h3e] = 8'hd1;
assign new_inv_sbox[8'h3f] = 8'h25;
assign new_inv_sbox[8'h40] = 8'h72;
assign new_inv_sbox[8'h41] = 8'hf8;
assign new_inv_sbox[8'h42] = 8'hf6;
assign new_inv_sbox[8'h43] = 8'h64;
assign new_inv_sbox[8'h44] = 8'h86;
assign new_inv_sbox[8'h45] = 8'h68;
assign new_inv_sbox[8'h46] = 8'h98;
assign new_inv_sbox[8'h47] = 8'h16;
assign new_inv_sbox[8'h48] = 8'hd4;
assign new_inv_sbox[8'h49] = 8'ha4;
assign new_inv_sbox[8'h4a] = 8'h5c;
assign new_inv_sbox[8'h4b] = 8'hcc;
assign new_inv_sbox[8'h4c] = 8'h5d;
assign new_inv_sbox[8'h4d] = 8'h65;
assign new_inv_sbox[8'h4e] = 8'hb6;
assign new_inv_sbox[8'h4f] = 8'h92;
assign new_inv_sbox[8'h50] = 8'h6c;
assign new_inv_sbox[8'h51] = 8'h70;
assign new_inv_sbox[8'h52] = 8'h48;
assign new_inv_sbox[8'h53] = 8'h50;
assign new_inv_sbox[8'h54] = 8'hfd;
assign new_inv_sbox[8'h55] = 8'hed;
assign new_inv_sbox[8'h56] = 8'hb9;
assign new_inv_sbox[8'h57] = 8'hda;
assign new_inv_sbox[8'h58] = 8'h5e;
assign new_inv_sbox[8'h59] = 8'h15;
assign new_inv_sbox[8'h5a] = 8'h46;
assign new_inv_sbox[8'h5b] = 8'h57;
assign new_inv_sbox[8'h5c] = 8'ha7;
assign new_inv_sbox[8'h5d] = 8'h8d;
assign new_inv_sbox[8'h5e] = 8'h9d;
assign new_inv_sbox[8'h5f] = 8'h84;
assign new_inv_sbox[8'h60] = 8'h90;
assign new_inv_sbox[8'h61] = 8'hd8;
assign new_inv_sbox[8'h62] = 8'hab;
assign new_inv_sbox[8'h63] = 8'h00;
assign new_inv_sbox[8'h64] = 8'h8c;
assign new_inv_sbox[8'h65] = 8'hbc;
assign new_inv_sbox[8'h66] = 8'hd3;
assign new_inv_sbox[8'h67] = 8'h0a;
assign new_inv_sbox[8'h68] = 8'hf7;
assign new_inv_sbox[8'h69] = 8'he4;
assign new_inv_sbox[8'h6a] = 8'h58;
assign new_inv_sbox[8'h6b] = 8'h05;
assign new_inv_sbox[8'h6c] = 8'hb8;
assign new_inv_sbox[8'h6d] = 8'hb3;
assign new_inv_sbox[8'h6e] = 8'h45;
assign new_inv_sbox[8'h6f] = 8'h06;
assign new_inv_sbox[8'h70] = 8'hd0;
assign new_inv_sbox[8'h71] = 8'h2c;
assign new_inv_sbox[8'h72] = 8'h1e;
assign new_inv_sbox[8'h73] = 8'h8f;
assign new_inv_sbox[8'h74] = 8'hca;
assign new_inv_sbox[8'h75] = 8'h3f;
assign new_inv_sbox[8'h76] = 8'h0f;
assign new_inv_sbox[8'h77] = 8'h02;
assign new_inv_sbox[8'h78] = 8'hc1;
assign new_inv_sbox[8'h79] = 8'haf;
assign new_inv_sbox[8'h7a] = 8'hbd;
assign new_inv_sbox[8'h7b] = 8'h03;
assign new_inv_sbox[8'h7c] = 8'h01;
assign new_inv_sbox[8'h7d] = 8'h13;
assign new_inv_sbox[8'h7e] = 8'h8a;
assign new_inv_sbox[8'h7f] = 8'h6b;
assign new_inv_sbox[8'h80] = 8'h3a;
assign new_inv_sbox[8'h81] = 8'h91;
assign new_inv_sbox[8'h82] = 8'h11;
assign new_inv_sbox[8'h83] = 8'h41;
assign new_inv_sbox[8'h84] = 8'h4f;
assign new_inv_sbox[8'h85] = 8'h67;
assign new_inv_sbox[8'h86] = 8'hdc;
assign new_inv_sbox[8'h87] = 8'hea;
assign new_inv_sbox[8'h88] = 8'h97;
assign new_inv_sbox[8'h89] = 8'hf2;
assign new_inv_sbox[8'h8a] = 8'hcf;
assign new_inv_sbox[8'h8b] = 8'hce;
assign new_inv_sbox[8'h8c] = 8'hf0;
assign new_inv_sbox[8'h8d] = 8'hb4;
assign new_inv_sbox[8'h8e] = 8'he6;
assign new_inv_sbox[8'h8f] = 8'h73;
assign new_inv_sbox[8'h90] = 8'h96;
assign new_inv_sbox[8'h91] = 8'hac;
assign new_inv_sbox[8'h92] = 8'h74;
assign new_inv_sbox[8'h93] = 8'h22;
assign new_inv_sbox[8'h94] = 8'he7;
assign new_inv_sbox[8'h95] = 8'had;
assign new_inv_sbox[8'h96] = 8'h35;
assign new_inv_sbox[8'h97] = 8'h85;
assign new_inv_sbox[8'h98] = 8'he2;
assign new_inv_sbox[8'h99] = 8'hf9;
assign new_inv_sbox[8'h9a] = 8'h37;
assign new_inv_sbox[8'h9b] = 8'he8;
assign new_inv_sbox[8'h9c] = 8'h1c;
assign new_inv_sbox[8'h9d] = 8'h75;
assign new_inv_sbox[8'h9e] = 8'hdf;
assign new_inv_sbox[8'h9f] = 8'h6e;
assign new_inv_sbox[8'ha0] = 8'h47;
assign new_inv_sbox[8'ha1] = 8'hf1;
assign new_inv_sbox[8'ha2] = 8'h1a;
assign new_inv_sbox[8'ha3] = 8'h71;
assign new_inv_sbox[8'ha4] = 8'h1d;
assign new_inv_sbox[8'ha5] = 8'h29;
assign new_inv_sbox[8'ha6] = 8'hc5;
assign new_inv_sbox[8'ha7] = 8'h89;
assign new_inv_sbox[8'ha8] = 8'h6f;
assign new_inv_sbox[8'ha9] = 8'hb7;
assign new_inv_sbox[8'haa] = 8'h62;
assign new_inv_sbox[8'hab] = 8'h0e;
assign new_inv_sbox[8'hac] = 8'haa;
assign new_inv_sbox[8'had] = 8'h18;
assign new_inv_sbox[8'hae] = 8'hbe;
assign new_inv_sbox[8'haf] = 8'h1b;
assign new_inv_sbox[8'hb0] = 8'hfc;
assign new_inv_sbox[8'hb1] = 8'h56;
assign new_inv_sbox[8'hb2] = 8'h3e;
assign new_inv_sbox[8'hb3] = 8'h4b;
assign new_inv_sbox[8'hb4] = 8'hc6;
assign new_inv_sbox[8'hb5] = 8'hd2;
assign new_inv_sbox[8'hb6] = 8'h79;
assign new_inv_sbox[8'hb7] = 8'h20;
assign new_inv_sbox[8'hb8] = 8'h9a;
assign new_inv_sbox[8'hb9] = 8'hdb;
assign new_inv_sbox[8'hba] = 8'hc0;
assign new_inv_sbox[8'hbb] = 8'hfe;
assign new_inv_sbox[8'hbc] = 8'h78;
assign new_inv_sbox[8'hbd] = 8'hcd;
assign new_inv_sbox[8'hbe] = 8'h5a;
assign new_inv_sbox[8'hbf] = 8'hf4;
assign new_inv_sbox[8'hc0] = 8'h1f;
assign new_inv_sbox[8'hc1] = 8'hdd;
assign new_inv_sbox[8'hc2] = 8'ha8;
assign new_inv_sbox[8'hc3] = 8'h33;
assign new_inv_sbox[8'hc4] = 8'h88;
assign new_inv_sbox[8'hc5] = 8'h07;
assign new_inv_sbox[8'hc6] = 8'hc7;
assign new_inv_sbox[8'hc7] = 8'h31;
assign new_inv_sbox[8'hc8] = 8'hb1;
assign new_inv_sbox[8'hc9] = 8'h12;
assign new_inv_sbox[8'hca] = 8'h10;
assign new_inv_sbox[8'hcb] = 8'h59;
assign new_inv_sbox[8'hcc] = 8'h27;
assign new_inv_sbox[8'hcd] = 8'h80;
assign new_inv_sbox[8'hce] = 8'hec;
assign new_inv_sbox[8'hcf] = 8'h5f;
assign new_inv_sbox[8'hd0] = 8'h60;
assign new_inv_sbox[8'hd1] = 8'h51;
assign new_inv_sbox[8'hd2] = 8'h7f;
assign new_inv_sbox[8'hd3] = 8'ha9;
assign new_inv_sbox[8'hd4] = 8'h19;
assign new_inv_sbox[8'hd5] = 8'hb5;
assign new_inv_sbox[8'hd6] = 8'h4a;
assign new_inv_sbox[8'hd7] = 8'h0d;
assign new_inv_sbox[8'hd8] = 8'h2d;
assign new_inv_sbox[8'hd9] = 8'he5;
assign new_inv_sbox[8'hda] = 8'h7a;
assign new_inv_sbox[8'hdb] = 8'h9f;
assign new_inv_sbox[8'hdc] = 8'h93;
assign new_inv_sbox[8'hdd] = 8'hc9;
assign new_inv_sbox[8'hde] = 8'h9c;
assign new_inv_sbox[8'hdf] = 8'hef;
assign new_inv_sbox[8'he0] = 8'ha0;
assign new_inv_sbox[8'he1] = 8'he0;
assign new_inv_sbox[8'he2] = 8'h3b;
assign new_inv_sbox[8'he3] = 8'h4d;
assign new_inv_sbox[8'he4] = 8'hae;
assign new_inv_sbox[8'he5] = 8'h2a;
assign new_inv_sbox[8'he6] = 8'hf5;
assign new_inv_sbox[8'he7] = 8'hb0;
assign new_inv_sbox[8'he8] = 8'hc8;
assign new_inv_sbox[8'he9] = 8'heb;
assign new_inv_sbox[8'hea] = 8'hbb;
assign new_inv_sbox[8'heb] = 8'h3c;
assign new_inv_sbox[8'hec] = 8'h83;
assign new_inv_sbox[8'hed] = 8'h53;
assign new_inv_sbox[8'hee] = 8'h99;
assign new_inv_sbox[8'hef] = 8'h61;
assign new_inv_sbox[8'hf0] = 8'h17;
assign new_inv_sbox[8'hf1] = 8'h2b;
assign new_inv_sbox[8'hf2] = 8'h04;
assign new_inv_sbox[8'hf3] = 8'h7e;
assign new_inv_sbox[8'hf4] = 8'hba;
assign new_inv_sbox[8'hf5] = 8'h77;
assign new_inv_sbox[8'hf6] = 8'hd6;
assign new_inv_sbox[8'hf7] = 8'h26;
assign new_inv_sbox[8'hf8] = 8'he1;
assign new_inv_sbox[8'hf9] = 8'h69;
assign new_inv_sbox[8'hfa] = 8'h14;
assign new_inv_sbox[8'hfb] = 8'h63;
assign new_inv_sbox[8'hfc] = 8'h55;
assign new_inv_sbox[8'hfd] = 8'h21;
assign new_inv_sbox[8'hfe] = 8'h0c;
assign new_inv_sbox[8'hff] = 8'h7d;

assign out_Subed = new_inv_sbox[in_toSub];
endmodule

Decryption/tb_InvSBox.v
`include "InvSBox.v"

module tb_InvSBox ();
    reg [7:0] in_toSub_tb;
    wire [7:0] out_Subed_tb;

    InvSBox ob(.in_toSub(in_toSub_tb), .out_Subed(out_Subed_tb));

    localparam period = 5;

    initial begin
        $dumpfile("tb_InvSBox.vcd");
        $dumpvars(0, tb_InvSBox);

        for (in_toSub_tb = 8'd0; in_toSub_tb <= 8'hff ; in_toSub_tb = in_toSub_tb + 1 ) begin
            #period;
        end
    end

    initial begin
        # (257*period) $finish;
    end

endmodule

Decryption/tb_InvSBox.vcd
$date
	Thu Apr 27 00:02:22 2023
$end
$version
	Icarus Verilog
$end
$timescale
	1s
$end
$scope module tb_InvSBox $end
$var wire 8 ! out_Subed_tb [7:0] $end
$var parameter 32 " period $end
$var reg 8 # in_toSub_tb [7:0] $end
$scope module ob $end
$var wire 8 $ in_toSub [7:0] $end
$var wire 8 % out_Subed [7:0] $end
$upscope $end
$upscope $end
$enddefinitions $end
$comment Show the parameter values. $end
$dumpall
b101 "
$end
#0
$dumpvars
b1010010 %
b0 $
b0 #
b1010010 !
$end
#5
b1001 !
b1001 %
b1 #
b1 $
#10
b1101010 !
b1101010 %
b10 #
b10 $
#15
b11010101 !
b11010101 %
b11 #
b11 $
#20
b110000 !
b110000 %
b100 #
b100 $
#25
b110110 !
b110110 %
b101 #
b101 $
#30
b10100101 !
b10100101 %
b110 #
b110 $
#35
b111000 !
b111000 %
b111 #
b111 $
#40
b10111111 !
b10111111 %
b1000 #
b1000 $
#45
b1000000 !
b1000000 %
b1001 #
b1001 $
#50
b10100011 !
b10100011 %
b1010 #
b1010 $
#55
b10011110 !
b10011110 %
b1011 #
b1011 $
#60
b10000001 !
b10000001 %
b1100 #
b1100 $
#65
b11110011 !
b11110011 %
b1101 #
b1101 $
#70
b11010111 !
b11010111 %
b1110 #
b1110 $
#75
b11111011 !
b11111011 %
b1111 #
b1111 $
#80
b1111100 !
b1111100 %
b10000 #
b10000 $
#85
b11100011 !
b11100011 %
b10001 #
b10001 $
#90
b111001 !
b111001 %
b10010 #
b10010 $
#95
b10000010 !
b10000010 %
b10011 #
b10011 $
#100
b10011011 !
b10011011 %
b10100 #
b10100 $
#105
b101111 !
b101111 %
b10101 #
b10101 $
#110
b11111111 !
b11111111 %
b10110 #
b10110 $
#115
b10000111 !
b10000111 %
b10111 #
b10111 $
#120
b110100 !
b110100 %
b11000 #
b11000 $
#125
b10001110 !
b10001110 %
b11001 #
b11001 $
#130
b1000011 !
b1000011 %
b11010 #
b11010 $
#135
b1000100 !
b1000100 %
b11011 #
b11011 $
#140
b11000100 !
b11000100 %
b11100 #
b11100 $
#145
b11011110 !
b11011110 %
b11101 #
b11101 $
#150
b11101001 !
b11101001 %
b11110 #
b11110 $
#155
b11001011 !
b11001011 %
b11111 #
b11111 $
#160
b1010100 !
b1010100 %
b100000 #
b100000 $
#165
b1111011 !
b1111011 %
b100001 #
b100001 $
#170
b10010100 !
b10010100 %
b100010 #
b100010 $
#175
b110010 !
b110010 %
b100011 #
b100011 $
#180
b10100110 !
b10100110 %
b100100 #
b100100 $
#185
b11000010 !
b11000010 %
b100101 #
b100101 $
#190
b100011 !
b100011 %
b100110 #
b100110 $
#195
b111101 !
b111101 %
b100111 #
b100111 $
#200
b11101110 !
b11101110 %
b101000 #
b101000 $
#205
b1001100 !
b1001100 %
b101001 #
b101001 $
#210
b10010101 !
b10010101 %
b101010 #
b101010 $
#215
b1011 !
b1011 %
b101011 #
b101011 $
#220
b1000010 !
b1000010 %
b101100 #
b101100 $
#225
b11111010 !
b11111010 %
b101101 #
b101101 $
#230
b11000011 !
b11000011 %
b101110 #
b101110 $
#235
b1001110 !
b1001110 %
b101111 #
b101111 $
#240
b1000 !
b1000 %
b110000 #
b110000 $
#245
b101110 !
b101110 %
b110001 #
b110001 $
#250
b10100001 !
b10100001 %
b110010 #
b110010 $
#255
b1100110 !
b1100110 %
b110011 #
b110011 $
#260
b101000 !
b101000 %
b110100 #
b110100 $
#265
b11011001 !
b11011001 %
b110101 #
b110101 $
#270
b100100 !
b100100 %
b110110 #
b110110 $
#275
b10110010 !
b10110010 %
b110111 #
b110111 $
#280
b1110110 !
b1110110 %
b111000 #
b111000 $
#285
b1011011 !
b1011011 %
b111001 #
b111001 $
#290
b10100010 !
b10100010 %
b111010 #
b111010 $
#295
b1001001 !
b1001001 %
b111011 #
b111011 $
#300
b1101101 !
b1101101 %
b111100 #
b111100 $
#305
b10001011 !
b10001011 %
b111101 #
b111101 $
#310
b11010001 !
b11010001 %
b111110 #
b111110 $
#315
b100101 !
b100101 %
b111111 #
b111111 $
#320
b1110010 !
b1110010 %
b1000000 #
b1000000 $
#325
b11111000 !
b11111000 %
b1000001 #
b1000001 $
#330
b11110110 !
b11110110 %
b1000010 #
b1000010 $
#335
b1100100 !
b1100100 %
b1000011 #
b1000011 $
#340
b10000110 !
b10000110 %
b1000100 #
b1000100 $
#345
b1101000 !
b1101000 %
b1000101 #
b1000101 $
#350
b10011000 !
b10011000 %
b1000110 #
b1000110 $
#355
b10110 !
b10110 %
b1000111 #
b1000111 $
#360
b11010100 !
b11010100 %
b1001000 #
b1001000 $
#365
b10100100 !
b10100100 %
b1001001 #
b1001001 $
#370
b1011100 !
b1011100 %
b1001010 #
b1001010 $
#375
b11001100 !
b11001100 %
b1001011 #
b1001011 $
#380
b1011101 !
b1011101 %
b1001100 #
b1001100 $
#385
b1100101 !
b1100101 %
b1001101 #
b1001101 $
#390
b10110110 !
b10110110 %
b1001110 #
b1001110 $
#395
b10010010 !
b10010010 %
b1001111 #
b1001111 $
#400
b1101100 !
b1101100 %
b1010000 #
b1010000 $
#405
b1110000 !
b1110000 %
b1010001 #
b1010001 $
#410
b1001000 !
b1001000 %
b1010010 #
b1010010 $
#415
b1010000 !
b1010000 %
b1010011 #
b1010011 $
#420
b11111101 !
b11111101 %
b1010100 #
b1010100 $
#425
b11101101 !
b11101101 %
b1010101 #
b1010101 $
#430
b10111001 !
b10111001 %
b1010110 #
b1010110 $
#435
b11011010 !
b11011010 %
b1010111 #
b1010111 $
#440
b1011110 !
b1011110 %
b1011000 #
b1011000 $
#445
b10101 !
b10101 %
b1011001 #
b1011001 $
#450
b1000110 !
b1000110 %
b1011010 #
b1011010 $
#455
b1010111 !
b1010111 %
b1011011 #
b1011011 $
#460
b10100111 !
b10100111 %
b1011100 #
b1011100 $
#465
b10001101 !
b10001101 %
b1011101 #
b1011101 $
#470
b10011101 !
b10011101 %
b1011110 #
b1011110 $
#475
b10000100 !
b10000100 %
b1011111 #
b1011111 $
#480
b10010000 !
b10010000 %
b1100000 #
b1100000 $
#485
b11011000 !
b11011000 %
b1100001 #
b1100001 $
#490
b10101011 !
b10101011 %
b1100010 #
b1100010 $
#495
b0 !
b0 %
b1100011 #
b1100011 $
#500
b10001100 !
b10001100 %
b1100100 #
b1100100 $
#505
b10111100 !
b10111100 %
b1100101 #
b1100101 $
#510
b11010011 !
b11010011 %
b1100110 #
b1100110 $
#515
b1010 !
b1010 %
b1100111 #
b1100111 $
#520
b11110111 !
b11110111 %
b1101000 #
b1101000 $
#525
b11100100 !
b11100100 %
b1101001 #
b1101001 $
#530
b1011000 !
b1011000 %
b1101010 #
b1101010 $
#535
b101 !
b101 %
b1101011 #
b1101011 $
#540
b10111000 !
b10111000 %
b1101100 #
b1101100 $
#545
b10110011 !
b10110011 %
b1101101 #
b1101101 $
#550
b1000101 !
b1000101 %
b1101110 #
b1101110 $
#555
b110 !
b110 %
b1101111 #
b1101111 $
#560
b11010000 !
b11010000 %
b1110000 #
b1110000 $
#565
b101100 !
b101100 %
b1110001 #
b1110001 $
#570
b11110 !
b11110 %
b1110010 #
b1110010 $
#575
b10001111 !
b10001111 %
b1110011 #
b1110011 $
#580
b11001010 !
b11001010 %
b1110100 #
b1110100 $
#585
b111111 !
b111111 %
b1110101 #
b1110101 $
#590
b1111 !
b1111 %
b1110110 #
b1110110 $
#595
b10 !
b10 %
b1110111 #
b1110111 $
#600
b11000001 !
b11000001 %
b1111000 #
b1111000 $
#605
b10101111 !
b10101111 %
b1111001 #
b1111001 $
#610
b10111101 !
b10111101 %
b1111010 #
b1111010 $
#615
b11 !
b11 %
b1111011 #
b1111011 $
#620
b1 !
b1 %
b1111100 #
b1111100 $
#625
b10011 !
b10011 %
b1111101 #
b1111101 $
#630
b10001010 !
b10001010 %
b1111110 #
b1111110 $
#635
b1101011 !
b1101011 %
b1111111 #
b1111111 $
#640
b111010 !
b111010 %
b10000000 #
b10000000 $
#645
b10010001 !
b10010001 %
b10000001 #
b10000001 $
#650
b10001 !
b10001 %
b10000010 #
b10000010 $
#655
b1000001 !
b1000001 %
b10000011 #
b10000011 $
#660
b1001111 !
b1001111 %
b10000100 #
b10000100 $
#665
b1100111 !
b1100111 %
b10000101 #
b10000101 $
#670
b11011100 !
b11011100 %
b10000110 #
b10000110 $
#675
b11101010 !
b11101010 %
b10000111 #
b10000111 $
#680
b10010111 !
b10010111 %
b10001000 #
b10001000 $
#685
b11110010 !
b11110010 %
b10001001 #
b10001001 $
#690
b11001111 !
b11001111 %
b10001010 #
b10001010 $
#695
b11001110 !
b11001110 %
b10001011 #
b10001011 $
#700
b11110000 !
b11110000 %
b10001100 #
b10001100 $
#705
b10110100 !
b10110100 %
b10001101 #
b10001101 $
#710
b11100110 !
b11100110 %
b10001110 #
b10001110 $
#715
b1110011 !
b1110011 %
b10001111 #
b10001111 $
#720
b10010110 !
b10010110 %
b10010000 #
b10010000 $
#725
b10101100 !
b10101100 %
b10010001 #
b10010001 $
#730
b1110100 !
b1110100 %
b10010010 #
b10010010 $
#735
b100010 !
b100010 %
b10010011 #
b10010011 $
#740
b11100111 !
b11100111 %
b10010100 #
b10010100 $
#745
b10101101 !
b10101101 %
b10010101 #
b10010101 $
#750
b110101 !
b110101 %
b10010110 #
b10010110 $
#755
b10000101 !
b10000101 %
b10010111 #
b10010111 $
#760
b11100010 !
b11100010 %
b10011000 #
b10011000 $
#765
b11111001 !
b11111001 %
b10011001 #
b10011001 $
#770
b110111 !
b110111 %
b10011010 #
b10011010 $
#775
b11101000 !
b11101000 %
b10011011 #
b10011011 $
#780
b11100 !
b11100 %
b10011100 #
b10011100 $
#785
b1110101 !
b1110101 %
b10011101 #
b10011101 $
#790
b11011111 !
b11011111 %
b10011110 #
b10011110 $
#795
b1101110 !
b1101110 %
b10011111 #
b10011111 $
#800
b1000111 !
b1000111 %
b10100000 #
b10100000 $
#805
b11110001 !
b11110001 %
b10100001 #
b10100001 $
#810
b11010 !
b11010 %
b10100010 #
b10100010 $
#815
b1110001 !
b1110001 %
b10100011 #
b10100011 $
#820
b11101 !
b11101 %
b10100100 #
b10100100 $
#825
b101001 !
b101001 %
b10100101 #
b10100101 $
#830
b11000101 !
b11000101 %
b10100110 #
b10100110 $
#835
b10001001 !
b10001001 %
b10100111 #
b10100111 $
#840
b1101111 !
b1101111 %
b10101000 #
b10101000 $
#845
b10110111 !
b10110111 %
b10101001 #
b10101001 $
#850
b1100010 !
b1100010 %
b10101010 #
b10101010 $
#855
b1110 !
b1110 %
b10101011 #
b10101011 $
#860
b10101010 !
b10101010 %
b10101100 #
b10101100 $
#865
b11000 !
b11000 %
b10101101 #
b10101101 $
#870
b10111110 !
b10111110 %
b10101110 #
b10101110 $
#875
b11011 !
b11011 %
b10101111 #
b10101111 $
#880
b11111100 !
b11111100 %
b10110000 #
b10110000 $
#885
b1010110 !
b1010110 %
b10110001 #
b10110001 $
#890
b111110 !
b111110 %
b10110010 #
b10110010 $
#895
b1001011 !
b1001011 %
b10110011 #
b10110011 $
#900
b11000110 !
b11000110 %
b10110100 #
b10110100 $
#905
b11010010 !
b11010010 %
b10110101 #
b10110101 $
#910
b1111001 !
b1111001 %
b10110110 #
b10110110 $
#915
b100000 !
b100000 %
b10110111 #
b10110111 $
#920
b10011010 !
b10011010 %
b10111000 #
b10111000 $
#925
b11011011 !
b11011011 %
b10111001 #
b10111001 $
#930
b11000000 !
b11000000 %
b10111010 #
b10111010 $
#935
b11111110 !
b11111110 %
b10111011 #
b10111011 $
#940
b1111000 !
b1111000 %
b10111100 #
b10111100 $
#945
b11001101 !
b11001101 %
b10111101 #
b10111101 $
#950
b1011010 !
b1011010 %
b10111110 #
b10111110 $
#955
b11110100 !
b11110100 %
b10111111 #
b10111111 $
#960
b11111 !
b11111 %
b11000000 #
b11000000 $
#965
b11011101 !
b11011101 %
b11000001 #
b11000001 $
#970
b10101000 !
b10101000 %
b11000010 #
b11000010 $
#975
b110011 !
b110011 %
b11000011 #
b11000011 $
#980
b10001000 !
b10001000 %
b11000100 #
b11000100 $
#985
b111 !
b111 %
b11000101 #
b11000101 $
#990
b11000111 !
b11000111 %
b11000110 #
b11000110 $
#995
b110001 !
b110001 %
b11000111 #
b11000111 $
#1000
b10110001 !
b10110001 %
b11001000 #
b11001000 $
#1005
b10010 !
b10010 %
b11001001 #
b11001001 $
#1010
b10000 !
b10000 %
b11001010 #
b11001010 $
#1015
b1011001 !
b1011001 %
b11001011 #
b11001011 $
#1020
b100111 !
b100111 %
b11001100 #
b11001100 $
#1025
b10000000 !
b10000000 %
b11001101 #
b11001101 $
#1030
b11101100 !
b11101100 %
b11001110 #
b11001110 $
#1035
b1011111 !
b1011111 %
b11001111 #
b11001111 $
#1040
b1100000 !
b1100000 %
b11010000 #
b11010000 $
#1045
b1010001 !
b1010001 %
b11010001 #
b11010001 $
#1050
b1111111 !
b1111111 %
b11010010 #
b11010010 $
#1055
b10101001 !
b10101001 %
b11010011 #
b11010011 $
#1060
b11001 !
b11001 %
b11010100 #
b11010100 $
#1065
b10110101 !
b10110101 %
b11010101 #
b11010101 $
#1070
b1001010 !
b1001010 %
b11010110 #
b11010110 $
#1075
b1101 !
b1101 %
b11010111 #
b11010111 $
#1080
b101101 !
b101101 %
b11011000 #
b11011000 $
#1085
b11100101 !
b11100101 %
b11011001 #
b11011001 $
#1090
b1111010 !
b1111010 %
b11011010 #
b11011010 $
#1095
b10011111 !
b10011111 %
b11011011 #
b11011011 $
#1100
b10010011 !
b10010011 %
b11011100 #
b11011100 $
#1105
b11001001 !
b11001001 %
b11011101 #
b11011101 $
#1110
b10011100 !
b10011100 %
b11011110 #
b11011110 $
#1115
b11101111 !
b11101111 %
b11011111 #
b11011111 $
#1120
b10100000 !
b10100000 %
b11100000 #
b11100000 $
#1125
b11100000 !
b11100000 %
b11100001 #
b11100001 $
#1130
b111011 !
b111011 %
b11100010 #
b11100010 $
#1135
b1001101 !
b1001101 %
b11100011 #
b11100011 $
#1140
b10101110 !
b10101110 %
b11100100 #
b11100100 $
#1145
b101010 !
b101010 %
b11100101 #
b11100101 $
#1150
b11110101 !
b11110101 %
b11100110 #
b11100110 $
#1155
b10110000 !
b10110000 %
b11100111 #
b11100111 $
#1160
b11001000 !
b11001000 %
b11101000 #
b11101000 $
#1165
b11101011 !
b11101011 %
b11101001 #
b11101001 $
#1170
b10111011 !
b10111011 %
b11101010 #
b11101010 $
#1175
b111100 !
b111100 %
b11101011 #
b11101011 $
#1180
b10000011 !
b10000011 %
b11101100 #
b11101100 $
#1185
b1010011 !
b1010011 %
b11101101 #
b11101101 $
#1190
b10011001 !
b10011001 %
b11101110 #
b11101110 $
#1195
b1100001 !
b1100001 %
b11101111 #
b11101111 $
#1200
b10111 !
b10111 %
b11110000 #
b11110000 $
#1205
b101011 !
b101011 %
b11110001 #
b11110001 $
#1210
b100 !
b100 %
b11110010 #
b11110010 $
#1215
b1111110 !
b1111110 %
b11110011 #
b11110011 $
#1220
b10111010 !
b10111010 %
b11110100 #
b11110100 $
#1225
b1110111 !
b1110111 %
b11110101 #
b11110101 $
#1230
b11010110 !
b11010110 %
b11110110 #
b11110110 $
#1235
b100110 !
b100110 %
b11110111 #
b11110111 $
#1240
b11100001 !
b11100001 %
b11111000 #
b11111000 $
#1245
b1101001 !
b1101001 %
b11111001 #
b11111001 $
#1250
b10100 !
b10100 %
b11111010 #
b11111010 $
#1255
b1100011 !
b1100011 %
b11111011 #
b11111011 $
#1260
b1010101 !
b1010101 %
b11111100 #
b11111100 $
#1265
b100001 !
b100001 %
b11111101 #
b11111101 $
#1270
b1100 !
b1100 %
b11111110 #
b11111110 $
#1275
b1111000 !
b1111000 %
b11111111 #
b11111111 $
#1280
b1010010 !
b1010010 %
b0 #
b0 $
#1285
b1001 !
b1001 %
b1 #
b1 $
