Encryption/sbox.v
module SBox (
    input wire [7:0] in_toSub,
    output wire [7:0] out_Subed
);
    
    assign out_Subed = (in_toSub == 8'h00) ? 8'h63 :
                       (in_toSub == 8'h01) ? 8'h7c :
                       (in_toSub == 8'h02) ? 8'h77 :
                       (in_toSub == 8'h03) ? 8'h7b :
                       (in_toSub == 8'h04) ? 8'hf2 :
                       (in_toSub == 8'h05) ? 8'h6b :
                       (in_toSub == 8'h06) ? 8'h6f :
                       (in_toSub == 8'h07) ? 8'hc5 :
                       (in_toSub == 8'h08) ? 8'h30 :
                       (in_toSub == 8'h09) ? 8'h01 :
                       (in_toSub == 8'h0a) ? 8'h67 :
                       (in_toSub == 8'h0b) ? 8'h2b :
                       (in_toSub == 8'h0c) ? 8'hfe :
                       (in_toSub == 8'h0d) ? 8'hd7 :
                       (in_toSub == 8'h0e) ? 8'hab :
                       (in_toSub == 8'h0f) ? 8'h76 :
                       //the first row
                       (in_toSub == 8'h10) ? 8'hca :
                       (in_toSub == 8'h11) ? 8'h82 :
                       (in_toSub == 8'h12) ? 8'hc9 :
                       (in_toSub == 8'h13) ? 8'h7d :
                       (in_toSub == 8'h14) ? 8'hfa :
                       (in_toSub == 8'h15) ? 8'h59 :
                       (in_toSub == 8'h16) ? 8'h47 :
                       (in_toSub == 8'h17) ? 8'hf0 :
                       (in_toSub == 8'h18) ? 8'had :
                       (in_toSub == 8'h19) ? 8'hd4 :
                       (in_toSub == 8'h1a) ? 8'ha2 :
                       (in_toSub == 8'h1b) ? 8'haf :
                       (in_toSub == 8'h1c) ? 8'h9c :
                       (in_toSub == 8'h1d) ? 8'ha4 :
                       (in_toSub == 8'h1e) ? 8'h72 :
                       (in_toSub == 8'h1f) ? 8'hc0 :
                       //the second row
                       (in_toSub == 8'h20) ? 8'hb7 :
                       (in_toSub == 8'h21) ? 8'hfd :
                       (in_toSub == 8'h22) ? 8'h93 :
                       (in_toSub == 8'h23) ? 8'h26 :
                       (in_toSub == 8'h24) ? 8'h36 :
                       (in_toSub == 8'h25) ? 8'h3f :
                       (in_toSub == 8'h26) ? 8'hf7 :
                       (in_toSub == 8'h27) ? 8'hcc :
                       (in_toSub == 8'h28) ? 8'h34 :
                       (in_toSub == 8'h29) ? 8'ha5 :
                       (in_toSub == 8'h2a) ? 8'he5 :
                       (in_toSub == 8'h2b) ? 8'hf1 :
                       (in_toSub == 8'h2c) ? 8'h71 :
                       (in_toSub == 8'h2d) ? 8'hd8 :
                       (in_toSub == 8'h2e) ? 8'h31 :
                       (in_toSub == 8'h2f) ? 8'h15 :
                       //row 3
                       (in_toSub == 8'h30) ? 8'h04 :
                       (in_toSub == 8'h31) ? 8'hc7 :
                       (in_toSub == 8'h32) ? 8'h23 :
                       (in_toSub == 8'h33) ? 8'hc3 :
                       (in_toSub == 8'h34) ? 8'h18 :
                       (in_toSub == 8'h35) ? 8'h96 :
                       (in_toSub == 8'h36) ? 8'h05 :
                       (in_toSub == 8'h37) ? 8'h9a :
                       (in_toSub == 8'h38) ? 8'h07 :
                       (in_toSub == 8'h39) ? 8'h12 :
                       (in_toSub == 8'h3a) ? 8'h80 :
                       (in_toSub == 8'h3b) ? 8'he2 :
                       (in_toSub == 8'h3c) ? 8'heb :
                       (in_toSub == 8'h3d) ? 8'h27 :
                       (in_toSub == 8'h3e) ? 8'hb2 :
                       (in_toSub == 8'h3f) ? 8'h75 :
                       //row 4
                       (in_toSub == 8'h40) ? 8'h09 :
                       (in_toSub == 8'h41) ? 8'h83 :
                       (in_toSub == 8'h42) ? 8'h2c :
                       (in_toSub == 8'h43) ? 8'h1a :
                       (in_toSub == 8'h44) ? 8'h1b :
                       (in_toSub == 8'h45) ? 8'h6e :
                       (in_toSub == 8'h46) ? 8'h5a :
                       (in_toSub == 8'h47) ? 8'ha0 :
                       (in_toSub == 8'h48) ? 8'h52 :
                       (in_toSub == 8'h49) ? 8'h3b :
                       (in_toSub == 8'h4a) ? 8'hd6 :
                       (in_toSub == 8'h4b) ? 8'hb3 :
                       (in_toSub == 8'h4c) ? 8'h29 :
                       (in_toSub == 8'h4d) ? 8'he3 :
                       (in_toSub == 8'h4e) ? 8'h2f :
                       (in_toSub == 8'h4f) ? 8'h84 :
                       //row 5
                       (in_toSub == 8'h50) ? 8'h53 :
                       (in_toSub == 8'h51) ? 8'hd1 :
                       (in_toSub == 8'h52) ? 8'h00 :
                       (in_toSub == 8'h53) ? 8'hed :
                       (in_toSub == 8'h54) ? 8'h20 :
                       (in_toSub == 8'h55) ? 8'hfc :
                       (in_toSub == 8'h56) ? 8'hb1 :
                       (in_toSub == 8'h57) ? 8'h5b :
                       (in_toSub == 8'h58) ? 8'h6a :
                       (in_toSub == 8'h59) ? 8'hcb :
                       (in_toSub == 8'h5a) ? 8'hbe :
                       (in_toSub == 8'h5b) ? 8'h39 :
                       (in_toSub == 8'h5c) ? 8'h4a :
                       (in_toSub == 8'h5d) ? 8'h4c :
                       (in_toSub == 8'h5e) ? 8'h58 :
                       (in_toSub == 8'h5f) ? 8'hcf :
                       //row 6 of index 5
                       (in_toSub == 8'h60) ? 8'hd0 :
                       (in_toSub == 8'h61) ? 8'hef :
                       (in_toSub == 8'h62) ? 8'haa :
                       (in_toSub == 8'h63) ? 8'hfb :
                       (in_toSub == 8'h64) ? 8'h43 :
                       (in_toSub == 8'h65) ? 8'h4d :
                       (in_toSub == 8'h66) ? 8'h33 :
                       (in_toSub == 8'h67) ? 8'h85 :
                       (in_toSub == 8'h68) ? 8'h45 :
                       (in_toSub == 8'h69) ? 8'hf9 :
                       (in_toSub == 8'h6a) ? 8'h02 :
                       (in_toSub == 8'h6b) ? 8'h7f :
                       (in_toSub == 8'h6c) ? 8'h50 :
                       (in_toSub == 8'h6d) ? 8'h3c :
                       (in_toSub == 8'h6e) ? 8'h9f :
                       (in_toSub == 8'h6f) ? 8'ha8 :
                       //row 7 of index 6
                       (in_toSub == 8'h70) ? 8'h51 :
                       (in_toSub == 8'h71) ? 8'ha3 :
                       (in_toSub == 8'h72) ? 8'h40 :
                       (in_toSub == 8'h73) ? 8'h8f :
                       (in_toSub == 8'h74) ? 8'h92 :
                       (in_toSub == 8'h75) ? 8'h9d :
                       (in_toSub == 8'h76) ? 8'h38 :
                       (in_toSub == 8'h77) ? 8'hf5 :
                       (in_toSub == 8'h78) ? 8'hbc :
                       (in_toSub == 8'h79) ? 8'hb6 :
                       (in_toSub == 8'h7a) ? 8'hda :
                       (in_toSub == 8'h7b) ? 8'h21 :
                       (in_toSub == 8'h7c) ? 8'h10 :
                       (in_toSub == 8'h7d) ? 8'hff :
                       (in_toSub == 8'h7e) ? 8'hf3 :
                       (in_toSub == 8'h7f) ? 8'hd2 :
                       //row 8 of index 7
                       (in_toSub == 8'h80) ? 8'hcd :
                       (in_toSub == 8'h81) ? 8'h0c :
                       (in_toSub == 8'h82) ? 8'h13 :
                       (in_toSub == 8'h83) ? 8'hec :
                       (in_toSub == 8'h84) ? 8'h5f :
                       (in_toSub == 8'h85) ? 8'h97 :
                       (in_toSub == 8'h86) ? 8'h44 :
                       (in_toSub == 8'h87) ? 8'h17 :
                       (in_toSub == 8'h88) ? 8'hc4 :
                       (in_toSub == 8'h89) ? 8'ha7 :
                       (in_toSub == 8'h8a) ? 8'h7e :
                       (in_toSub == 8'h8b) ? 8'h3d :
                       (in_toSub == 8'h8c) ? 8'h64 :
                       (in_toSub == 8'h8d) ? 8'h5d :
                       (in_toSub == 8'h8e) ? 8'h19 :
                       (in_toSub == 8'h8f) ? 8'h73 :
                       //row 9 of index 8
                       (in_toSub == 8'h90) ? 8'h60 :
                       (in_toSub == 8'h91) ? 8'h81 :
                       (in_toSub == 8'h92) ? 8'h4f :
                       (in_toSub == 8'h93) ? 8'hdc :
                       (in_toSub == 8'h94) ? 8'h22 :
                       (in_toSub == 8'h95) ? 8'h2a :
                       (in_toSub == 8'h96) ? 8'h90 :
                       (in_toSub == 8'h97) ? 8'h88 :
                       (in_toSub == 8'h98) ? 8'h46 :
                       (in_toSub == 8'h99) ? 8'hee :
                       (in_toSub == 8'h9a) ? 8'hb8 :
                       (in_toSub == 8'h9b) ? 8'h14 :
                       (in_toSub == 8'h9c) ? 8'hde :
                       (in_toSub == 8'h9d) ? 8'h5e :
                       (in_toSub == 8'h9e) ? 8'h0b :
                       (in_toSub == 8'h9f) ? 8'hdb :
                       //row 10 of index 9
                       (in_toSub == 8'ha0) ? 8'he0 :
                       (in_toSub == 8'ha1) ? 8'h32 :
                       (in_toSub == 8'ha2) ? 8'h3a :
                       (in_toSub == 8'ha3) ? 8'h0a :
                       (in_toSub == 8'ha4) ? 8'h49 :
                       (in_toSub == 8'ha5) ? 8'h06 :
                       (in_toSub == 8'ha6) ? 8'h24 :
                       (in_toSub == 8'ha7) ? 8'h5c :
                       (in_toSub == 8'ha8) ? 8'hc2 :
                       (in_toSub == 8'ha9) ? 8'hd3 :
                       (in_toSub == 8'haa) ? 8'hac :
                       (in_toSub == 8'hab) ? 8'h62 :
                       (in_toSub == 8'hac) ? 8'h91 :
                       (in_toSub == 8'had) ? 8'h95 :
                       (in_toSub == 8'hae) ? 8'he4 :
                       (in_toSub == 8'haf) ? 8'h79 :
                       //row 11 of index a
                       (in_toSub == 8'hb0) ? 8'he7 :
                       (in_toSub == 8'hb1) ? 8'hc8 :
                       (in_toSub == 8'hb2) ? 8'h37 :
                       (in_toSub == 8'hb3) ? 8'h6d :
                       (in_toSub == 8'hb4) ? 8'h8d :
                       (in_toSub == 8'hb5) ? 8'hd5 :
                       (in_toSub == 8'hb6) ? 8'h4e :
                       (in_toSub == 8'hb7) ? 8'ha9 :
                       (in_toSub == 8'hb8) ? 8'h6c :
                       (in_toSub == 8'hb9) ? 8'h56 :
                       (in_toSub == 8'hba) ? 8'hf4 :
                       (in_toSub == 8'hbb) ? 8'hea :
                       (in_toSub == 8'hbc) ? 8'h65 :
                       (in_toSub == 8'hbd) ? 8'h7a :
                       (in_toSub == 8'hbe) ? 8'hae :
                       (in_toSub == 8'hbf) ? 8'h08 :
                       //row 12 of index b
                       (in_toSub == 8'hc0) ? 8'hba :
                       (in_toSub == 8'hc1) ? 8'h78 :
                       (in_toSub == 8'hc2) ? 8'h25 :
                       (in_toSub == 8'hc3) ? 8'h2e :
                       (in_toSub == 8'hc4) ? 8'h1c :
                       (in_toSub == 8'hc5) ? 8'ha6 :
                       (in_toSub == 8'hc6) ? 8'hb4 :
                       (in_toSub == 8'hc7) ? 8'hc6 :
                       (in_toSub == 8'hc8) ? 8'he8 :
                       (in_toSub == 8'hc9) ? 8'hdd :
                       (in_toSub == 8'hca) ? 8'h74 :
                       (in_toSub == 8'hcb) ? 8'h1f :
                       (in_toSub == 8'hcc) ? 8'h4b :
                       (in_toSub == 8'hcd) ? 8'hbd :
                       (in_toSub == 8'hce) ? 8'h8b :
                       (in_toSub == 8'hcf) ? 8'h8a :
                       //row 13 of index c
                       (in_toSub == 8'hd0) ? 8'h70 :
                       (in_toSub == 8'hd1) ? 8'h3e :
                       (in_toSub == 8'hd2) ? 8'hb5 :
                       (in_toSub == 8'hd3) ? 8'h66 :
                       (in_toSub == 8'hd4) ? 8'h48 :
                       (in_toSub == 8'hd5) ? 8'h03 :
                       (in_toSub == 8'hd6) ? 8'hf6 :
                       (in_toSub == 8'hd7) ? 8'h0e :
                       (in_toSub == 8'hd8) ? 8'h61 :
                       (in_toSub == 8'hd9) ? 8'h35 :
                       (in_toSub == 8'hda) ? 8'h57 :
                       (in_toSub == 8'hdb) ? 8'hb9 :
                       (in_toSub == 8'hdc) ? 8'h86 :
                       (in_toSub == 8'hdd) ? 8'hc1 :
                       (in_toSub == 8'hde) ? 8'h1d :
                       (in_toSub == 8'hdf) ? 8'h9e :
                       //row 14 of index d
                       (in_toSub == 8'he0) ? 8'he1 :
                       (in_toSub == 8'he1) ? 8'hf8 :
                       (in_toSub == 8'he2) ? 8'h98 :
                       (in_toSub == 8'he3) ? 8'h11 :
                       (in_toSub == 8'he4) ? 8'h69 :
                       (in_toSub == 8'he5) ? 8'hd9 :
                       (in_toSub == 8'he6) ? 8'h8e :
                       (in_toSub == 8'he7) ? 8'h94 :
                       (in_toSub == 8'he8) ? 8'h9b :
                       (in_toSub == 8'he9) ? 8'h1e :
                       (in_toSub == 8'hea) ? 8'h87 :
                       (in_toSub == 8'heb) ? 8'he9 :
                       (in_toSub == 8'hec) ? 8'hce :
                       (in_toSub == 8'hed) ? 8'h55 :
                       (in_toSub == 8'hee) ? 8'h28 :
                       (in_toSub == 8'hef) ? 8'hdf :
                       //row 15 of index e
                       (in_toSub == 8'hf0) ? 8'h8c :
                       (in_toSub == 8'hf1) ? 8'ha1 :
                       (in_toSub == 8'hf2) ? 8'h89 :
                       (in_toSub == 8'hf3) ? 8'h0d :
                       (in_toSub == 8'hf4) ? 8'hbf :
                       (in_toSub == 8'hf5) ? 8'he6 :
                       (in_toSub == 8'hf6) ? 8'h42 :
                       (in_toSub == 8'hf7) ? 8'h68 :
                       (in_toSub == 8'hf8) ? 8'h41 :
                       (in_toSub == 8'hf9) ? 8'h99 :
                       (in_toSub == 8'hfa) ? 8'h2d :
                       (in_toSub == 8'hfb) ? 8'h0f :
                       (in_toSub == 8'hfc) ? 8'hb0 :
                       (in_toSub == 8'hfd) ? 8'h54 :
                       (in_toSub == 8'hfe) ? 8'hbb :
                       (in_toSub == 8'hff) ? 8'h16 :
                       8'bxxxxxxxx;
                       //row 16 of index f
endmodule

Encryption/tb_sbox.v
`include "SBox.v"

module tb_SBox ();
    reg [7:0] in_toSub_tb;
    wire [7:0] out_Subed_tb;

    SBox ob1(.in_toSub(in_toSub_tb), .out_Subed(out_Subed_tb));

    localparam period = 10;

    initial begin
        $dumpfile("tb_SBox.vcd");
        $dumpvars(0, tb_SBox);

        for (in_toSub_tb = 8'd0; in_toSub_tb <= 8'hff ; in_toSub_tb = in_toSub_tb + 1 ) begin
            #period;
        end
    end

    initial begin
        # (257*period) $finish;
    end
endmodule

Encryption/tb_sbox.vcd
$date
	Wed Apr 26 23:45:16 2023
$end
$version
	Icarus Verilog
$end
$timescale
	1s
$end
$scope module tb_SBox $end
$var wire 8 ! out_Subed_tb [7:0] $end
$var parameter 32 " period $end
$var reg 8 # in_toSub_tb [7:0] $end
$scope module ob1 $end
$var wire 8 $ in_toSub [7:0] $end
$var wire 8 % out_Subed [7:0] $end
$upscope $end
$upscope $end
$enddefinitions $end
$comment Show the parameter values. $end
$dumpall
b1010 "
$end
#0
$dumpvars
b1100011 %
b0 $
b0 #
b1100011 !
$end
#10
b1111100 !
b1111100 %
b1 #
b1 $
#20
b1110111 !
b1110111 %
b10 #
b10 $
#30
b1111011 !
b1111011 %
b11 #
b11 $
#40
b11110010 !
b11110010 %
b100 #
b100 $
#50
b1101011 !
b1101011 %
b101 #
b101 $
#60
b1101111 !
b1101111 %
b110 #
b110 $
#70
b11000101 !
b11000101 %
b111 #
b111 $
#80
b110000 !
b110000 %
b1000 #
b1000 $
#90
b1 !
b1 %
b1001 #
b1001 $
#100
b1100111 !
b1100111 %
b1010 #
b1010 $
#110
b101011 !
b101011 %
b1011 #
b1011 $
#120
b11111110 !
b11111110 %
b1100 #
b1100 $
#130
b11010111 !
b11010111 %
b1101 #
b1101 $
#140
b10101011 !
b10101011 %
b1110 #
b1110 $
#150
b1110110 !
b1110110 %
b1111 #
b1111 $
#160
b11001010 !
b11001010 %
b10000 #
b10000 $
#170
b10000010 !
b10000010 %
b10001 #
b10001 $
#180
b11001001 !
b11001001 %
b10010 #
b10010 $
#190
b1111101 !
b1111101 %
b10011 #
b10011 $
#200
b11111010 !
b11111010 %
b10100 #
b10100 $
#210
b1011001 !
b1011001 %
b10101 #
b10101 $
#220
b1000111 !
b1000111 %
b10110 #
b10110 $
#230
b11110000 !
b11110000 %
b10111 #
b10111 $
#240
b10101101 !
b10101101 %
b11000 #
b11000 $
#250
b11010100 !
b11010100 %
b11001 #
b11001 $
#260
b10100010 !
b10100010 %
b11010 #
b11010 $
#270
b10101111 !
b10101111 %
b11011 #
b11011 $
#280
b10011100 !
b10011100 %
b11100 #
b11100 $
#290
b10100100 !
b10100100 %
b11101 #
b11101 $
#300
b1110010 !
b1110010 %
b11110 #
b11110 $
#310
b11000000 !
b11000000 %
b11111 #
b11111 $
#320
b10110111 !
b10110111 %
b100000 #
b100000 $
#330
b11111101 !
b11111101 %
b100001 #
b100001 $
#340
b10010011 !
b10010011 %
b100010 #
b100010 $
#350
b100110 !
b100110 %
b100011 #
b100011 $
#360
b110110 !
b110110 %
b100100 #
b100100 $
#370
b111111 !
b111111 %
b100101 #
b100101 $
#380
b11110111 !
b11110111 %
b100110 #
b100110 $
#390
b11001100 !
b11001100 %
b100111 #
b100111 $
#400
b110100 !
b110100 %
b101000 #
b101000 $
#410
b10100101 !
b10100101 %
b101001 #
b101001 $
#420
b11100101 !
b11100101 %
b101010 #
b101010 $
#430
b11110001 !
b11110001 %
b101011 #
b101011 $
#440
b1110001 !
b1110001 %
b101100 #
b101100 $
#450
b11011000 !
b11011000 %
b101101 #
b101101 $
#460
b110001 !
b110001 %
b101110 #
b101110 $
#470
b10101 !
b10101 %
b101111 #
b101111 $
#480
b100 !
b100 %
b110000 #
b110000 $
#490
b11000111 !
b11000111 %
b110001 #
b110001 $
#500
b100011 !
b100011 %
b110010 #
b110010 $
#510
b11000011 !
b11000011 %
b110011 #
b110011 $
#520
b11000 !
b11000 %
b110100 #
b110100 $
#530
b10010110 !
b10010110 %
b110101 #
b110101 $
#540
b101 !
b101 %
b110110 #
b110110 $
#550
b10011010 !
b10011010 %
b110111 #
b110111 $
#560
b111 !
b111 %
b111000 #
b111000 $
#570
b10010 !
b10010 %
b111001 #
b111001 $
#580
b10000000 !
b10000000 %
b111010 #
b111010 $
#590
b11100010 !
b11100010 %
b111011 #
b111011 $
#600
b11101011 !
b11101011 %
b111100 #
b111100 $
#610
b100111 !
b100111 %
b111101 #
b111101 $
#620
b10110010 !
b10110010 %
b111110 #
b111110 $
#630
b1110101 !
b1110101 %
b111111 #
b111111 $
#640
b1001 !
b1001 %
b1000000 #
b1000000 $
#650
b10000011 !
b10000011 %
b1000001 #
b1000001 $
#660
b101100 !
b101100 %
b1000010 #
b1000010 $
#670
b11010 !
b11010 %
b1000011 #
b1000011 $
#680
b11011 !
b11011 %
b1000100 #
b1000100 $
#690
b1101110 !
b1101110 %
b1000101 #
b1000101 $
#700
b1011010 !
b1011010 %
b1000110 #
b1000110 $
#710
b10100000 !
b10100000 %
b1000111 #
b1000111 $
#720
b1010010 !
b1010010 %
b1001000 #
b1001000 $
#730
b111011 !
b111011 %
b1001001 #
b1001001 $
#740
b11010110 !
b11010110 %
b1001010 #
b1001010 $
#750
b10110011 !
b10110011 %
b1001011 #
b1001011 $
#760
b101001 !
b101001 %
b1001100 #
b1001100 $
#770
b11100011 !
b11100011 %
b1001101 #
b1001101 $
#780
b101111 !
b101111 %
b1001110 #
b1001110 $
#790
b10000100 !
b10000100 %
b1001111 #
b1001111 $
#800
b1010011 !
b1010011 %
b1010000 #
b1010000 $
#810
b11010001 !
b11010001 %
b1010001 #
b1010001 $
#820
b0 !
b0 %
b1010010 #
b1010010 $
#830
b11101101 !
b11101101 %
b1010011 #
b1010011 $
#840
b100000 !
b100000 %
b1010100 #
b1010100 $
#850
b11111100 !
b11111100 %
b1010101 #
b1010101 $
#860
b10110001 !
b10110001 %
b1010110 #
b1010110 $
#870
b1011011 !
b1011011 %
b1010111 #
b1010111 $
#880
b1101010 !
b1101010 %
b1011000 #
b1011000 $
#890
b11001011 !
b11001011 %
b1011001 #
b1011001 $
#900
b10111110 !
b10111110 %
b1011010 #
b1011010 $
#910
b111001 !
b111001 %
b1011011 #
b1011011 $
#920
b1001010 !
b1001010 %
b1011100 #
b1011100 $
#930
b1001100 !
b1001100 %
b1011101 #
b1011101 $
#940
b1011000 !
b1011000 %
b1011110 #
b1011110 $
#950
b11001111 !
b11001111 %
b1011111 #
b1011111 $
#960
b11010000 !
b11010000 %
b1100000 #
b1100000 $
#970
b11101111 !
b11101111 %
b1100001 #
b1100001 $
#980
b10101010 !
b10101010 %
b1100010 #
b1100010 $
#990
b11111011 !
b11111011 %
b1100011 #
b1100011 $
#1000
b1000011 !
b1000011 %
b1100100 #
b1100100 $
#1010
b1001101 !
b1001101 %
b1100101 #
b1100101 $
#1020
b110011 !
b110011 %
b1100110 #
b1100110 $
#1030
b10000101 !
b10000101 %
b1100111 #
b1100111 $
#1040
b1000101 !
b1000101 %
b1101000 #
b1101000 $
#1050
b11111001 !
b11111001 %
b1101001 #
b1101001 $
#1060
b10 !
b10 %
b1101010 #
b1101010 $
#1070
b1111111 !
b1111111 %
b1101011 #
b1101011 $
#1080
b1010000 !
b1010000 %
b1101100 #
b1101100 $
#1090
b111100 !
b111100 %
b1101101 #
b1101101 $
#1100
b10011111 !
b10011111 %
b1101110 #
b1101110 $
#1110
b10101000 !
b10101000 %
b1101111 #
b1101111 $
#1120
b1010001 !
b1010001 %
b1110000 #
b1110000 $
#1130
b10100011 !
b10100011 %
b1110001 #
b1110001 $
#1140
b1000000 !
b1000000 %
b1110010 #
b1110010 $
#1150
b10001111 !
b10001111 %
b1110011 #
b1110011 $
#1160
b10010010 !
b10010010 %
b1110100 #
b1110100 $
#1170
b10011101 !
b10011101 %
b1110101 #
b1110101 $
#1180
b111000 !
b111000 %
b1110110 #
b1110110 $
#1190
b11110101 !
b11110101 %
b1110111 #
b1110111 $
#1200
b10111100 !
b10111100 %
b1111000 #
b1111000 $
#1210
b10110110 !
b10110110 %
b1111001 #
b1111001 $
#1220
b11011010 !
b11011010 %
b1111010 #
b1111010 $
#1230
b100001 !
b100001 %
b1111011 #
b1111011 $
#1240
b10000 !
b10000 %
b1111100 #
b1111100 $
#1250
b11111111 !
b11111111 %
b1111101 #
b1111101 $
#1260
b11110011 !
b11110011 %
b1111110 #
b1111110 $
#1270
b11010010 !
b11010010 %
b1111111 #
b1111111 $
#1280
b11001101 !
b11001101 %
b10000000 #
b10000000 $
#1290
b1100 !
b1100 %
b10000001 #
b10000001 $
#1300
b10011 !
b10011 %
b10000010 #
b10000010 $
#1310
b11101100 !
b11101100 %
b10000011 #
b10000011 $
#1320
b1011111 !
b1011111 %
b10000100 #
b10000100 $
#1330
b10010111 !
b10010111 %
b10000101 #
b10000101 $
#1340
b1000100 !
b1000100 %
b10000110 #
b10000110 $
#1350
b10111 !
b10111 %
b10000111 #
b10000111 $
#1360
b11000100 !
b11000100 %
b10001000 #
b10001000 $
#1370
b10100111 !
b10100111 %
b10001001 #
b10001001 $
#1380
b1111110 !
b1111110 %
b10001010 #
b10001010 $
#1390
b111101 !
b111101 %
b10001011 #
b10001011 $
#1400
b1100100 !
b1100100 %
b10001100 #
b10001100 $
#1410
b1011101 !
b1011101 %
b10001101 #
b10001101 $
#1420
b11001 !
b11001 %
b10001110 #
b10001110 $
#1430
b1110011 !
b1110011 %
b10001111 #
b10001111 $
#1440
b1100000 !
b1100000 %
b10010000 #
b10010000 $
#1450
b10000001 !
b10000001 %
b10010001 #
b10010001 $
#1460
b1001111 !
b1001111 %
b10010010 #
b10010010 $
#1470
b11011100 !
b11011100 %
b10010011 #
b10010011 $
#1480
b100010 !
b100010 %
b10010100 #
b10010100 $
#1490
b101010 !
b101010 %
b10010101 #
b10010101 $
#1500
b10010000 !
b10010000 %
b10010110 #
b10010110 $
#1510
b10001000 !
b10001000 %
b10010111 #
b10010111 $
#1520
b1000110 !
b1000110 %
b10011000 #
b10011000 $
#1530
b11101110 !
b11101110 %
b10011001 #
b10011001 $
#1540
b10111000 !
b10111000 %
b10011010 #
b10011010 $
#1550
b10100 !
b10100 %
b10011011 #
b10011011 $
#1560
b11011110 !
b11011110 %
b10011100 #
b10011100 $
#1570
b1011110 !
b1011110 %
b10011101 #
b10011101 $
#1580
b1011 !
b1011 %
b10011110 #
b10011110 $
#1590
b11011011 !
b11011011 %
b10011111 #
b10011111 $
#1600
b11100000 !
b11100000 %
b10100000 #
b10100000 $
#1610
b110010 !
b110010 %
b10100001 #
b10100001 $
#1620
b111010 !
b111010 %
b10100010 #
b10100010 $
#1630
b1010 !
b1010 %
b10100011 #
b10100011 $
#1640
b1001001 !
b1001001 %
b10100100 #
b10100100 $
#1650
b110 !
b110 %
b10100101 #
b10100101 $
#1660
b100100 !
b100100 %
b10100110 #
b10100110 $
#1670
b1011100 !
b1011100 %
b10100111 #
b10100111 $
#1680
b11000010 !
b11000010 %
b10101000 #
b10101000 $
#1690
b11010011 !
b11010011 %
b10101001 #
b10101001 $
#1700
b10101100 !
b10101100 %
b10101010 #
b10101010 $
#1710
b1100010 !
b1100010 %
b10101011 #
b10101011 $
#1720
b10010001 !
b10010001 %
b10101100 #
b10101100 $
#1730
b10010101 !
b10010101 %
b10101101 #
b10101101 $
#1740
b11100100 !
b11100100 %
b10101110 #
b10101110 $
#1750
b1111001 !
b1111001 %
b10101111 #
b10101111 $
#1760
b11100111 !
b11100111 %
b10110000 #
b10110000 $
#1770
b11001000 !
b11001000 %
b10110001 #
b10110001 $
#1780
b110111 !
b110111 %
b10110010 #
b10110010 $
#1790
b1101101 !
b1101101 %
b10110011 #
b10110011 $
#1800
b10001101 !
b10001101 %
b10110100 #
b10110100 $
#1810
b11010101 !
b11010101 %
b10110101 #
b10110101 $
#1820
b1001110 !
b1001110 %
b10110110 #
b10110110 $
#1830
b10101001 !
b10101001 %
b10110111 #
b10110111 $
#1840
b1101100 !
b1101100 %
b10111000 #
b10111000 $
#1850
b1010110 !
b1010110 %
b10111001 #
b10111001 $
#1860
b11110100 !
b11110100 %
b10111010 #
b10111010 $
#1870
b11101010 !
b11101010 %
b10111011 #
b10111011 $
#1880
b1100101 !
b1100101 %
b10111100 #
b10111100 $
#1890
b1111010 !
b1111010 %
b10111101 #
b10111101 $
#1900
b10101110 !
b10101110 %
b10111110 #
b10111110 $
#1910
b1000 !
b1000 %
b10111111 #
b10111111 $
#1920
b10111010 !
b10111010 %
b11000000 #
b11000000 $
#1930
b1111000 !
b1111000 %
b11000001 #
b11000001 $
#1940
b100101 !
b100101 %
b11000010 #
b11000010 $
#1950
b101110 !
b101110 %
b11000011 #
b11000011 $
#1960
b11100 !
b11100 %
b11000100 #
b11000100 $
#1970
b10100110 !
b10100110 %
b11000101 #
b11000101 $
#1980
b10110100 !
b10110100 %
b11000110 #
b11000110 $
#1990
b11000110 !
b11000110 %
b11000111 #
b11000111 $
#2000
b11101000 !
b11101000 %
b11001000 #
b11001000 $
#2010
b11011101 !
b11011101 %
b11001001 #
b11001001 $
#2020
b1110100 !
b1110100 %
b11001010 #
b11001010 $
#2030
b11111 !
b11111 %
b11001011 #
b11001011 $
#2040
b1001011 !
b1001011 %
b11001100 #
b11001100 $
#2050
b10111101 !
b10111101 %
b11001101 #
b11001101 $
#2060
b10001011 !
b10001011 %
b11001110 #
b11001110 $
#2070
b10001010 !
b10001010 %
b11001111 #
b11001111 $
#2080
b1110000 !
b1110000 %
b11010000 #
b11010000 $
#2090
b111110 !
b111110 %
b11010001 #
b11010001 $
#2100
b10110101 !
b10110101 %
b11010010 #
b11010010 $
#2110
b1100110 !
b1100110 %
b11010011 #
b11010011 $
#2120
b1001000 !
b1001000 %
b11010100 #
b11010100 $
#2130
b11 !
b11 %
b11010101 #
b11010101 $
#2140
b11110110 !
b11110110 %
b11010110 #
b11010110 $
#2150
b1110 !
b1110 %
b11010111 #
b11010111 $
#2160
b1100001 !
b1100001 %
b11011000 #
b11011000 $
#2170
b110101 !
b110101 %
b11011001 #
b11011001 $
#2180
b1010111 !
b1010111 %
b11011010 #
b11011010 $
#2190
b10111001 !
b10111001 %
b11011011 #
b11011011 $
#2200
b10000110 !
b10000110 %
b11011100 #
b11011100 $
#2210
b11000001 !
b11000001 %
b11011101 #
b11011101 $
#2220
b11101 !
b11101 %
b11011110 #
b11011110 $
#2230
b10011110 !
b10011110 %
b11011111 #
b11011111 $
#2240
b11100001 !
b11100001 %
b11100000 #
b11100000 $
#2250
b11111000 !
b11111000 %
b11100001 #
b11100001 $
#2260
b10011000 !
b10011000 %
b11100010 #
b11100010 $
#2270
b10001 !
b10001 %
b11100011 #
b11100011 $
#2280
b1101001 !
b1101001 %
b11100100 #
b11100100 $
#2290
b11011001 !
b11011001 %
b11100101 #
b11100101 $
#2300
b10001110 !
b10001110 %
b11100110 #
b11100110 $
#2310
b10010100 !
b10010100 %
b11100111 #
b11100111 $
#2320
b10011011 !
b10011011 %
b11101000 #
b11101000 $
#2330
b11110 !
b11110 %
b11101001 #
b11101001 $
#2340
b10000111 !
b10000111 %
b11101010 #
b11101010 $
#2350
b11101001 !
b11101001 %
b11101011 #
b11101011 $
#2360
b11001110 !
b11001110 %
b11101100 #
b11101100 $
#2370
b1010101 !
b1010101 %
b11101101 #
b11101101 $
#2380
b101000 !
b101000 %
b11101110 #
b11101110 $
#2390
b11011111 !
b11011111 %
b11101111 #
b11101111 $
#2400
b10001100 !
b10001100 %
b11110000 #
b11110000 $
#2410
b10100001 !
b10100001 %
b11110001 #
b11110001 $
#2420
b10001001 !
b10001001 %
b11110010 #
b11110010 $
#2430
b1101 !
b1101 %
b11110011 #
b11110011 $
#2440
b10111111 !
b10111111 %
b11110100 #
b11110100 $
#2450
b11100110 !
b11100110 %
b11110101 #
b11110101 $
#2460
b1000010 !
b1000010 %
b11110110 #
b11110110 $
#2470
b1101000 !
b1101000 %
b11110111 #
b11110111 $
#2480
b1000001 !
b1000001 %
b11111000 #
b11111000 $
#2490
b10011001 !
b10011001 %
b11111001 #
b11111001 $
#2500
b101101 !
b101101 %
b11111010 #
b11111010 $
#2510
b1111 !
b1111 %
b11111011 #
b11111011 $
